LICENSE.txt
MANIFEST.in
Readme.md
setup.py
asset_bender/__init__.py
asset_bender/bundling.py
asset_bender/http.py
asset_bender.egg-info/PKG-INFO
asset_bender.egg-info/SOURCES.txt
asset_bender.egg-info/dependency_links.txt
asset_bender.egg-info/requires.txt
asset_bender.egg-info/top_level.txt
asset_bender/templates/asset_bender/scaffold/bender_boilerplate_js.html
asset_bender/templates/asset_bender/scaffold/end_of_body.html
asset_bender/templates/asset_bender/scaffold/head.html
asset_bender/templatetags/__init__.py
asset_bender/templatetags/asset_bender_tags.py
asset_bender/templatetags/test/__init__.py
asset_bender/templatetags/test/test_asset_bender_tags.py