Metadata-Version: 1.0
Name: asset-bender
Version: 0.1.21
Summary: A django runtime implementation for Asset Bender
Home-page: https://github.com/HubSpot/asset_bender_django
Author: HubSpot Dev Team
Author-email: devteam+asset_bender_django@hubspot.com
License: LICENSE.txt
Platform: UNKNOWN
